Workbook
Name ВидыДеятельности: #REF!

Sheet оценка проекта и долгового риск
A1: Блок 1. Показатели для ввода
A2: Показатель | B2: Источник1 | C2: Источник2 | D2: Временной период | E2: Комментарий
A3: Долгосрочные активы | B3: Баланс предприятия | C3: Инвестиционные проект | D3: 3 предшествующих года и горизонт инвестпроекта | E3: Данные в ячейках голубого цвета на листах 2, 3,4, 6 содержат формулы, в обычных ячейках - вводимые данные.
A4: Краткосрочные активы | B4: Баланс предприятия | C4: Инвестиционные проект | D4: 3 предшествующих года и горизонт инвестпроекта
A5: Собственный капитал | B5: Баланс предприятия | C5: Инвестиционные проект | D5: 3 предшествующих года и горизонт инвестпроекта
A6: Долгосрочные обязательства | B6: Баланс предприятия | C6: Инвестиционные проект | D6: 3 предшествующих года и горизонт инвестпроекта
A7: Краткосрочные обязательства | B7: Баланс предприятия | C7: Инвестиционные проект | D7: 3 предшествующих года и горизонт инвестпроекта
A8: Чистая прибыль | B8: Отчета о прибылях и убытках | C8: Инвестиционные проект | D8: 3 предшествующих года и горизонт инвестпроекта
A9: Прибыль до налогообложения (EBT) | B9: Отчета о прибылях и убытках | C9: Инвестиционные проект | D9: 3 предшествующих года и данные по инвестпроекту
A10: Амортизация | B10: Баланс основных средств предприятия | C10: Инвестиционные проект | D10: Горизонт инвестпроекта | E10: В бухгалтерском смысле (НСБУ) амортизация является частью операционных расходов (OPEX) и распределена между строками 020, 040 и 050.
A11: Текущие (Операционные) расходы (OPEX) | B11: Отчета о прибылях и убытках | C11: Инвестиционные проект | D11: Горизонт инвестпроекта | E11: OPEX = Себестоимость реализованной продукции (стр. 020) + Управленческие расходы (стр. 040) + Расходы на реализацию (стр. 050) При расчете показателя EBITDA используется «очищенный» показатель — (OPEX за вычетом амортизации).
A12: Адаптированный расчет EBITDA | B12: расчетный показатель (см. Методологическое замечание 2) | C12: Инвестиционные проект | D12: Горизонт инвестпроекта | E12: 1)EBITDA =Прибыль до налогообложения(EBT) +Процентные платежи + Амортизация; или 2) EBITDA = Выручка (от реализации продукции, товаров, работ, услуг) (стр. 010) – [ (Себестоимость реализованной продукции, товаров, работ, услуг) (стр. 020) + (Управленческие расходы) (стр. 040) + (Расходы на реализацию) (стр. 050) – Амортизация ]
A13: Прибыль до уплаты процентов и налогов (EBIT) | B13: расчетный показатель (см. Методологическое замечание 2) | C13: Инвестиционные проект | D13: Горизонт инвестпроекта
A14: Налоговая ставка (%) | C14: Инвестиционные проект | D14: Горизонт инвестпроекта
A15: Капитальные затраты (CAPEX) | C15: Инвестиционные проект | D15: Горизонт инвестпроекта
A16: Изменение чистого оборотного капитала | C16: Инвестиционные проект | D16: Горизонт инвестпроекта
A17: Новые кредиты и их параметры
A18: Сумма кредита ( отдельно по валютам) | C18: Инвестиционные проект | D18: Горизонт инвестпроекта
A19: Ставка по кредиту (%) | C19: Инвестиционные проект | D19: Горизонт инвестпроекта
A20: Проценты по кредиту | C20: Инвестиционные проект | D20: Горизонт инвестпроекта
A21: График погашения кредита | C21: Инвестиционные проект | D21: Горизонт инвестпроекта
A22: Доля долга в иностранной валюте | C22: Инвестиционные проект | D22: Горизонт инвестпроекта
A23: Займы других организаций и их параметры | C23: Инвестиционные проект | D23: Горизонт инвестпроекта
A24: Сумма займа (по каждому займу) | C24: Инвестиционные проект | D24: Горизонт инвестпроекта
A25: Ставка по займу (%) | C25: Инвестиционные проект | D25: Горизонт инвестпроекта
A26: График погашения основного долга | C26: Инвестиционные проект | D26: Горизонт инвестпроекта
A27: Особые условия | C27: Инвестиционные проект | D27: Горизонт инвестпроекта
A28: Финансовая аренда (лизинг) и его параметры
A29: Новые договоры лизинга | C29: Инвестиционные проект | D29: Горизонт инвестпроекта
A30: Аванс (первоначальный платёж) | C30: Инвестиционные проект | D30: Горизонт инвестпроекта
A31: Ставка лизинга (%) | C31: Инвестиционные проект | D31: Горизонт инвестпроекта
A32: График погашения основного долга | C32: Инвестиционные проект | D32: Горизонт инвестпроекта
A33: Выкупная стоимость | C33: Инвестиционные проект | D33: Горизонт инвестпроекта
A34: Ценные бумаги
A35: Выпуск ценных бумаг | C35: Инвестиционные проект | D35: Горизонт инвестпроекта
A36: Номинал | C36: Инвестиционные проект | D36: Горизонт инвестпроекта
A37: Купонная ставка (%) | C37: Инвестиционные проект | D37: Горизонт инвестпроекта
A38: Погашение номинала | C38: Инвестиционные проект | D38: Горизонт инвестпроекта
A39: Купонные выплаты
A40: Государственное участие | C40: Инвестиционные проект | D40: Горизонт инвестпроекта
A41: Компенсация процентов | C41: Инвестиционные проект | D41: Горизонт инвестпроекта
A42: Субсидии/гранты | C42: Инвестиционные проект | D42: Горизонт инвестпроекта
A43: Гарантии | C43: Инвестиционные проект | D43: Горизонт инвестпроекта
A44: Существующие долгосрочные кредиты, займы организации
A45: Остаток на начало
A46: Ставка (%)
A47: График погашения основного долга
A49: Блок 2. Принятые обозначения и сокращения
A50: Сокращения | B50: Расшифровка | C50: Комментарий
A51: КА | B51: Краткосрочные активы | C51: Текущие активы проекта
A52: К0 | B52: Краткосрочные обязательства | C52: Обязательства до 1 года
A53: ДА | B53: Долгосрочные активы | C53: Обязательства до 1 года
A54: СК | B54: Собственный капитал | C54: Среднегодовой
A55: ДС | B55: Долговой сервис ( обслуживание долга) | C55: Выплаты процентов + погашение основного долга
A56: Кпз | B56: Коэффициент покрытия задолженности | C56: Денежный поток /платежи по долгу (основной долг+проценты)
A57: КПП (ICR) | B57: Коэффициент покрытия процентов | C57: (Прибыль до налогообложения +процентные платежи)/процентные платежи
A58: CAPEX | B58: Капитальные затраты | C58: Инвестиции в проект
A59: WACC | B59: Средневзвешенная стоимость капитала | C59: Ставка дисконтирования
A60: NPV | B60: Чистая приведённая стоимость | C60: Оценка стоимости проекта
A61: IRR (ВНД) | B61: Внутренняя норма доходности | C61: Процентная ставка, при которой чистая приведённая стоимость (NPV) равна 0.
... A63: FX | B63: Валютный эффект | C63: Влияние изменения курса валюты на показатели проекта
A65: Блок 3.Связь между листами.
A67: Лист | B67: Содержимое | C67: Связь | D67: Комментарий
A68: Финансовая устойчивость | B68: Балансовые коэффициенты за предыдущие три года (ликвидность, автономия, рентабельность) | C68: Сравниваются с отраслевыми нормативами
A69: Оценка проекта | B69: Денежные потоки, чистая приведённая стоимость, внутренняя норма доходности, индекс прибыльности, срок окупаемости, коэффициент покрытия долга | C69: Использует отраслевой WACC для расчётов | D69: Отраслевой WACC используется как нормативная ставка дисконтирования. В оценке проекта ВНД сопоставляется с WACC: если ВНД ≥ WACC, проект считается экономически целесообразным. Чем выше WACC, тем выше порог доходности, который должен обеспечить проект
A70: Стресс‑тесты | B70: Покрытие основного долга, покрытие всех обязательств, чувствительность доходности, предел ставки кредита, буфер собственного капитала и др. | C70: Дополняют оценку проекта
A71: Отраслевые нормативы и WACC | B71: Нормативы ликвидности и отраслевые значения WACC | C71: Справочник для всех расчётов
A72: Итоговая оценка | B72: Сводный вывод + цветовой индикатор | C72: Объединяет результаты и даёт заключение
A75: Блок 4.Методологические замечания

Sheet 2.Фин устойчивость предпр  
C1: Название и код
B2: Отрасль (ОКЭД) | C2: 015 Смешанное сельское хозяйство
B3: Блок 1. Баланс предприятия за предыдущие 3 года | D3: Год 1 | F3: Год 2 | H3: Год 3
A4: № строки | B4: Показатель / Коэффициент | C4: Формула / комментарий | D4: на начало года | E4: на конец года | F4: на начало года | G4: на конец года | H4: на начало года | I4: на конец года | J4: Среднее значение за 3 года | K4: Норма (ссылка) | L4: Соответствие | M4: Знак светофора | N4: Примечания
A5: 1 | B5: Долгосрочные активы активы | C5: Значение берётся из баланса | D5: 280 | E5: 300 | F5: 300 | G5: 320 | H5: 320 | I5: 340 | J5: — | O5: Срееднегодовые
A6: 2 | B6: Краткосрочные активы | C6: Значение берётся из баланса | D6: 140 | E6: 150 | F6: 150 | G6: 160 | H6: 160 | I6: 170 | J6: — | O6: рассчитывается по данным баланса
A7: 3 | B7: Собственный капитал | C7: Значение берётся из баланса | D7: 240 | E7: 250 | F7: 250 | G7: 270 | H7: 270 | I7: 290 | J7: —
A8: 4 | B8: Долгосрочные обязательства | C8: Значение берётся из баланса | D8: 130 | E8: 120 | F8: 120 | G8: 110 | H8: 110 | I8: 100 | J8: —
A9: 5 | B9: Краткосрочные обязательства | C9: Значение берётся из баланса | D9: 90 | E9: 80 | F9: 80 | G9: 85 | H9: 85 | I9: 90 | J9: —
A10: 6 | B10: Итого активы | C10: Долгосрочные активы+Краткосрочные активы | D10: =D5+D6 -> 420 | E10: =E5+E6 -> 450 | F10: =F5+F6 -> 450 | G10: =G5+G6 -> 480 | H10: =H5+H6 -> 480 | I10: =I5+I6 -> 510
A11: 7 | B11: Чистая прибыль | C11: Значение берётся из баланса | D11: — | E11: 25 | F11: — | G11: 30 | H11: — | I11: 35 | J11: —
B12: Блок 2. Финансовые коэффициенты(оценка состояния за 3 года).
A13: 8
A14: 9 | B14: Финансовый леверидж (отношение долга к собственному капиталу ) | C14: (Долгосрочные+Краткосрочные обязательства)/собственный капитал [(стр.4+стр.5)/стр.3] | D14: =(D8+D9)/D7 -> 0.91666667 | E14: =(E8+E9)/E7 -> 0.8 | F14: =(F8+F9)/F7 -> 0.8 | G14: =(G8+G9)/G7 -> 0.72222222 | H14: =(H8+H9)/H7 -> 0.72222222 | I14: =(I8+I9)/I7 -> 0.65517241 | J14: =((D14+E14)/2+(F14+G14)/2+(H14+I14)/2)/3 -> 0.76938059 | K14: =VLOOKUP($C$2,'5.Отрасл нормативы и WACC '!$C$2:$K$175,7,FALSE) -> 0.7 | L14: =IFERROR(IF(J14<=K14,"Да",IF(J14<=K14*1.1,"Пограничное","Нет")),"") -> Пограничное | M14: =IF(PROPER(L14)="ДА",1, IF(PROPER(L14)="ПОГРАНИЧНОЕ",0.5, IF(PROPER(L14)="НЕТ",0,""))) -> 0.5
A15: 9 | B15: Рентабельность активов (ROA) | C15: Чистая прибыль / Средняя стоимость активов [стр.7/(стр.6t+стр.6t-1)/2] | E15: =E11/((E10+D10)/2) -> 0.057471264 | G15: =G11/((G10+F10)/2) -> 0.064516129 | I15: =I11/((I10+H10)/2) -> 0.070707071 | J15: =(E15+G15+I15)/3 -> 0.064231488 | K15: =VLOOKUP($C$2,'5.Отрасл нормативы и WACC '!$C$2:$K$175,5,FALSE) -> 0.03 | L15: =IFERROR(IF(J15>=K15,"Да",IF(J15>=K15*0.9,"Пограничное","Нет")),"") -> Да | M15: =IF(PROPER(L15)="ДА",1, IF(PROPER(L15)="ПОГРАНИЧНОЕ",0.5, IF(PROPER(L15)="НЕТ",0,""))) -> 1 | N15: WACC часто сравнивают с ROA в упрощенных моделях анализа. Это дает общее представление о том, насколько доходность всего имущества предприятия покрывает среднюю стоимость его финансирования.
A16: 10 | B16: Рентабельность собственного капитала (ROE) | C16: Чистая прибыль / среднегодовой собственный капитал [стр.7/(стр.3t+стр.3t-1)/2] | E16: =E11/((E7+D7)/2) -> 0.10204082 | G16: =G11/((G7+F7)/2) -> 0.11538462 | I16: =I11/((I7+H7)/2) -> 0.125 | J16: =(E16+G16+I16)/3 -> 0.11414181 | K16: =J16-(--VLOOKUP($C$2,'5.Отрасл нормативы и WACC '!C2:M175,11,FALSE)) -> 0.074762404 | L16: =IF(K16>0.000001,"Да",IF(K16<-0.000001,"Нет","Равно")) -> Да | M16: =IF(UPPER(TRIM($L$16))="ДА",1, IF(UPPER(TRIM($L$16))="НЕТ",0, IF(UPPER(TRIM($L$16))="РАВНО",0.5,""))) -> 1 | N16: — Если ROE выше среднеотраслевого → компания работает эффективнее конкурентов, создаёт дополнительную стоимость для собственников. — Если ROE ниже среднеотраслевого → эффективность капитала уступает отрасли, собственники теряют в сравнении с альтернативами. — Если ROE равен среднеотраслевому → компания находится на уровне рынка, без преимущества или отставания.
A17: 11 | B17: Коэффициент текущей ликвидности | C17: Краткосрочные активы /Краткосрочные обязательства [стр.2/стр.5] | D17: =D6/D9 -> 1.5555556 | E17: =E6/E9 -> 1.875 | F17: =F6/F9 -> 1.875 | G17: =G6/G9 -> 1.8823529 | H17: =H6/H9 -> 1.8823529 | I17: =I6/I9 -> 1.8888889 | J17: =AVERAGE(D17:I17) -> 1.8265251 | K17: =VLOOKUP($C$2,'5.Отрасл нормативы и WACC '!$C$2:$I$175,2,FALSE) -> 1.5 | L17: =IFERROR(IF(J17>=K17,"Да",IF(J17>=K17*0.9,"Пограничное","Нет")),"") -> Да | M17: =IF(PROPER(L17)="ДА",1, IF(PROPER(L17)="ПОГРАНИЧНОЕ",0.5, IF(PROPER(L17)="НЕТ",0,""))) -> 1
A18: 12 | B18: Коэффициент обеспеченности собственными оборотными средствами | C18: (Собственный капитал + долгосрочные обязательства - долгосрочные активы) / краткосрочные активы [(стр.3+стр.4-стр.1)/стр.2] | D18: =(D7+D8-D5)/D6 -> 0.64285714 | E18: =(E7+E8-E5)/E6 -> 0.46666667 | F18: =(F7+F8-F5)/F6 -> 0.46666667 | G18: =(G7+G8-G5)/G6 -> 0.375 | H18: =(H7+H8-H5)/H6 -> 0.375 | I18: =(I7+I8-I5)/I6 -> 0.29411765 | J18: =AVERAGE(D18:I18) -> 0.43671802 | K18: =VLOOKUP($C$2,'5.Отрасл нормативы и WACC '!$C$2:$K$175,3,FALSE) -> 0.2 | L18: =IFERROR(IF(J18>=K18,"Да",IF(J18>=K18*0.9,"Пограничное","Нет")),"") -> Да | M18: =IF(PROPER(L18)="ДА",1, IF(PROPER(L18)="ПОГРАНИЧНОЕ",0.5, IF(PROPER(L18)="НЕТ",0,""))) -> 1
A19: 13 | B19: Коэффициент обеспеченности обязательств активами | C19: (краткосрочные обязательства+Долгосрочные обязательства)/ активы [(стр.4+стр.5)/стр.6] | D19: =(D8+D9)/D10 -> 0.52380952 | F19: 1.9 | H19: 2.1 | J19: =AVERAGE(D19:H19) -> 1.5079365 | K19: =VLOOKUP($C$2,'5.Отрасл нормативы и WACC '!$C$2:$K$175,4,FALSE) -> 0.85 | L19: =IFERROR(IF(J19>=K19,"Да",IF(J19>=K19*0.9,"Пограничное","Нет")),"") -> Да | M19: =IF(PROPER(L19)="ДА",1, IF(PROPER(L19)="ПОГРАНИЧНОЕ",0.5, IF(PROPER(L19)="НЕТ",0,""))) -> 1
A20: 14 | B20: Коэффициент автономии (буфер собственного капитала) | C20: Собственный капитал / Активы [стр.3/стр.6] | D20: =D7/D10 -> 0.57142857 | E20: =E7/E10 -> 0.55555556 | F20: =F7/F10 -> 0.55555556 | G20: =G7/G10 -> 0.5625 | H20: =H7/H10 -> 0.5625 | I20: =I7/I10 -> 0.56862745 | J20: =AVERAGE(D20:H20) -> 0.56150794 | K20: =VLOOKUP($C$2,'5.Отрасл нормативы и WACC '!$C$2:$K$175,6,FALSE) -> 0.5 | L20: =IFERROR(IF(J20>=K20,"Да",IF(J20>=K20*0.9,"Пограничное","Нет")),"") -> Да | M20: =IF(PROPER(L20)="ДА",1, IF(PROPER(L20)="ПОГРАНИЧНОЕ",0.5, IF(PROPER(L20)="НЕТ",0,""))) -> 1

Sheet 3.Исх проект данные и риски  
A1: № строки | B1: Показатель | C1: Формула | D1: 0-й год проекта | E1: 1-й год проекта | F1: 2-й год проекта | G1: 3-й год проекта | H1: Комментарии
B2: Блок 1. Базовые показатели проекта
B3: Единица измерения: тыс. руб.
A4: 1 | B4: Выручка | C4: Данные инвестпроекта | D4: 700 | E4: 860 | F4: 1000 | G4: 1100
A5: 2 | B5: Текущие (операционные) расходы (OPEX) | C5: Отчета о прибылях и убытках: OPEX = Себестоимость реализованной продукции (стр. 020) + Управленческие расходы (стр. 040) + Расходы на реализацию (стр. 050) | D5: 450 | E5: 500 | F5: 540 | G5: 580 | H5: При расчете показателя EBITDA вторым методом используется «очищенный» показатель — (OPEX за вычетом амортизации) (см. стр.108)
A6: 3 | B6: Амортизация | C6: Баланс основных средств | D6: 50 | E6: 50 | F6: 50 | G6: 50
A7: 4 | B7: Проценты по существующим заемным средствам | C7: Проценты по существующим займам из блока 7[стр.87] | D7: =D103 -> 2.2 | E7: =E103 -> 1.76 | F7: =F103 -> 1.32 | G7: =G103 -> 0.88
A8: 5 | B8: Проценты по новым заемным средствам | C8: из блока «Заемные средства» [стр.33 + стр.44+стр.54+стр.64+стр.74-стр.79] | D8: =D43+D55+D66+D77+D88-D94 -> 0 | E8: =E43+E55+E66+E77+E88-E94 -> 80.6 | F8: =F43+F55+F66+F77+F88-F94 -> 83.8394 | G8: =G43+G55+G66+G77+G88-G94 -> 64.786283
A9: 6 | B9: Итого проценты = | C9: сумма строк [стр.4 + стр.5] | D9: =D7+D8 -> 2.2 | E9: =E7+E8 -> 82.36 | F9: =F7+F8 -> 85.1594 | G9: =G7+G8 -> 65.666283
A10: 7 | B10: Прибыль до налогообложения (EBT) | C10: Данные инвестпроекта | D10: 200 | E10: 310 | F10: 390 | G10: 450 | H10: Прибыль до налогообложения (EBT) — одновременно налоговая база для расчёта налога на прибыль.
A11: 8 | B11: EBITDA (адаптированный расчёт) | C11: Прибыль до налогообложения+Проценты+Амортизация [стр.7 + стр.6 + стр.3] | D11: =D10+D9+D6 -> 252.2 | E11: =E10+E9+E6 -> 442.36 | F11: =F10+F9+F6 -> 525.1594 | G11: =G10+G9+G6 -> 565.66628
A12: 9 | B12: Налоговая ставка (%) | D12: 0.2 | E12: 0.2 | F12: 0.2 | G12: 0.2
A13: 10 | B13: Налоги | C13: Налоговая база × ставка 20%) [стр.8 × стр.9] | D13: =D10*D12 -> 40 | E13: =E10*E12 -> 62 | F13: =F10*F12 -> 78 | G13: =G10*G12 -> 90
A14: 11 | B14: Чистая прибыль | C14: Налоговая база – Налоги [стр.8 – стр.10] | D14: =D10-D13 -> 160 | E14: =E10-E13 -> 248 | F14: =F10-F13 -> 312 | G14: =G10-G13 -> 360
A15: 12 | B15: Капитальные затраты (CAPEX) | D15: 700 | E15: 80 | F15: 60 | G15: 0
A16: 13 | B16: Прирост чистого оборотного капитала | C16: (краткосрочные активы – краткосрочные обязательства на начало периода) – (краткосрочные активы – краткосрочные обязательства на конец периода) | D16: -100 | E16: 30 | F16: 20 | G16: -10
A17: 14 | B17: Денежный поток (для обслуживания долга) | C17: Чистая прибыль + Амортизация – CAPEX ± Δчистого оборотного капитала [стр.11 + стр.3 – стр.12 ± стр.13] | D17: =D14+D6-D15+D16 -> -590 | E17: =E14+E6-E15+E16 -> 248 | F17: =F14+F6-F15+F16 -> 322 | G17: =G14+G6-G15+G16 -> 400
A18: 15 | B18: NPV | C18: WACC – денежные потоки | D18: =NPV(0.12,E17:G17)+D17 -> 172.8371
A19: 16 | B19: Внутренняя норма доходности (IRR) | C19: денежные потоки | D19: =IRR(D17:G17) -> 0.2702066
B20: Блок 2. Баланс
B21: Единица измерения: тыс. руб.
A22: 17 | B22: Краткосрочные активы | D22: 430 | E22: 440 | F22: 450 | G22: 460
A23: 18 | B23: Краткосрочные обязательства | D23: 300 | E23: 310 | F23: 320 | G23: 330
A24: 19 | B24: Долгосрочные активы | D24: 1550 | E24: 1510 | F24: 1470 | G24: 1430
A25: 20 | B25: Долгосрочные обязательства | D25: 887 | E25: 877 | F25: 867 | G25: 857
A26: 21 | B26: Собственный капитал | D26: 1550 | E26: 1510 | F26: 1470 | G26: 1430
A27: 22 | B27: Всего активов | C27: Красткосрочные + Долгосрочные | D27: =D22 + D24 -> 1980 | E27: =E22 + E24 -> 1950 | F27: =F22 + F24 -> 1920 | G27: =G22 + G24 -> 1890
A28: 23 | B28: Всего обязательств | C28: Краткосрочные + Долгосрочные | D28: =D23 + D25 -> 1187 | E28: =E23 + E25 -> 1187 | F28: =F23 + F25 -> 1187 | G28: =G23 + G25 -> 1187
B29: Блок 3. Коэффициенты устойчивости и рентабельности
B30: Единица измерения: доли
A31: 24 | B31: Коэффициент текущей ликвидности | C31: Краткосрочные активы /краткосрочные обязательства [стр.17/ стр.18] | D31: =D22 / D23 -> 1.4333333 | E31: =E22 / E23 -> 1.4193548 | F31: =F22 / F23 -> 1.40625 | G31: =G22 / G23 -> 1.3939394
A32: 25 | B32: Коэффициент финансовой независимости (автономии) (Кфн) | C32: Собственный капитал / Активы [стр.21/ стр.22] | D32: =D26 / D27 -> 0.78282828 | E32: =E26 / E27 -> 0.77435897 | F32: =F26 / F27 -> 0.765625 | G32: =G26 / G27 -> 0.75661376
A33: 26 | B33: Коэффициент обеспеченности собственными оборотными средствами | C33: (Собственный капитал + долгосрочные обязательства - долгосрочные активы) / краткосрочные активы [стр.21 + стр.20 – стр.19)/ стр.17] | D33: =(D26+D25 - D24) / D22 -> 2.0627907 | E33: =(E26+E25 - E24) / E22 -> 1.9931818 | F33: =(F26+F25 - F24) / F22 -> 1.9266667 | G33: =(G26+G25 - G24) / G22 -> 1.8630435
A34: 27 | B34: Коэффициент обеспеченности обязательств активами (Ка) | C34: Обязательства/Активы [стр.23/ стр.22] | D34: =D28/D27 -> 0.59949495 | E34: =E28/E27 -> 0.60871795 | F34: =F28/F27 -> 0.61822917 | G34: =G28/G27 -> 0.62804233
A35: 28 | B35: Рентабельность активов (Ра) | C35: Чистая прибыль / Активы(среднегодовые) [стр.11/ стр.22] | D35: =D14/D27 -> 0.080808081 | E35: =E14/E27 -> 0.12717949 | F35: =F14/F27 -> 0.1625 | G35: =G14/G27 -> 0.19047619
A36: 29 | B36: Рентабельность капитала (ROE) | C36: Чистая прибыль / Собственный капитал(среднегодовой) [стр.11/ стр.21] | D36: =D14/D26 -> 0.10322581 | E36: =E14/E26 -> 0.16423841 | F36: =F14/F26 -> 0.2122449 | G36: =G14/G26 -> 0.25174825
B37: Блок 4.Параметры заемных средств
B38: Единица измерения: тыс. руб.
B39: 1. Параметры кредита в национальной валюте
A40: 30 | B40: Сумма кредита на начало периода | C40: Равна остатку на конец предыдущего периода [стр.36 по графе t–1] | D40: 0 | E40: =D46 -> 300 | F40: =E46 -> 230 | G40: =F46 -> 153
A41: 31 | B41: Выдачи кредита | C41: Вводимое значение | D41: 300 | E41: 0 | F41: 0 | G41: 0
A42: 32 | B42: Ставка кредита (%) | C42: Применяется к остатку на начало периода | D42: 0.1 | E42: 0.1 | F42: 0.1 | G42: 0.1
A43: 33 | B43: Проценты по кредиту | C43: Ставка × Остаток долга на начало периода [стр.32 × стр.30] | D43: =D42 * D40 -> 0 | E43: =E42 * E40 -> 30 | F43: =F42 * F40 -> 23 | G43: =G42 * G40 -> 15.3
A44: 34 | B44: Погашение основного долга | C44: Вводимое значение | D44: 0 | E44: 100 | F44: 100 | G44: 100
A45: 35 | B45: Платежи по кредиту | C45: Погашение + Проценты × (1 – Флаг капитализации) [стр.34 + стр.33 × (1 – стр.37)] | D45: =D44+D43*(1-D47) -> 0 | E45: =E44+E43*(1-E47) -> 100 | F45: =F44+F43*(1-F47) -> 100 | G45: =G44+G43*(1-G47) -> 100
A46: 36 | B46: Остаток кредита на конец периода | C46: Остаток на начало + Выдачи – Погашение + Проценты × Флаг капитализации [стр.30 + стр.31 – стр.34 + стр.33 × стр.37] | D46: =D40 + D41 -D44+ D43*D47 -> 300 | E46: =E40 + E41 -E44+ E43*E47 -> 230 | F46: =F40 + F41 -F44+ F43*F47 -> 153 | G46: =G40 + G41 -G44+ G43*G47 -> 68.3
A47: 37 | B47: Флаг капитализации | C47: (0- без капитализации %. 1- с капитализацией %) | D47: 1 | E47: 1 | F47: 1 | G47: 1
B48: 2. Параметры кредита в иностранной валюте
A49: 38 | B49: Остаток кредита в валюте на начало периода | C49: Равен остатку на конец предыдущего периода [стр.48 по графе t–1] | D49: 0 | E49: =D59 -> 100 | F49: =E59 -> 72.9 | G49: =F59 -> 44.1198
A50: 39 | B50: Курс пересчёта | C50: Устанавливается вручную или через формулу | D50: 3 | E50: 3 | F50: 3 | G50: 3
A51: 40 | B51: Эквивалент в рублях | C51: Остаток в валюте × курс [стр.38 × стр.39] | D51: =D49*D50 -> 0 | E51: =E49*E50 -> 300 | F51: =F49*F50 -> 218.7 | G51: =G49*G50 -> 132.3594
A52: 41 | B52: Выдачи кредита | C52: Вводимое значение | D52: 100 | E52: 0 | F52: 0 | G52: 0
A53: 42 | B53: Ставка кредита (%) | C53: Вводимое значение (применяется к остатку на начало) | D53: 0.062 | E53: 0.062 | F53: 0.062 | G53: 0.062
A54: 43 | B54: Проценты по кредиту в валюте | C54: Ставка * Остаток долга на начало периода [стр.42 × стр.38] | D54: =D53*D49 -> 0 | E54: =E53*E49 -> 6.2 | F54: =F53*F49 -> 4.5198 | G54: =G53*G49 -> 2.7354276
A55: 44 | B55: Проценты по кредиту в рублях | C55: Проценты (в валюте) × курс [стр.43 × стр.39] | D55: =D54*D50 -> 0 | E55: =E54*E50 -> 18.6 | F55: =F54*F50 -> 13.5594 | G55: =G54*G50 -> 8.2062828
A56: 45 | B56: Погашение основного долга ( в валюте) | C56: Вводимое значение | D56: 0 | E56: 33.3 | F56: 33.3 | G56: 33.3
A57: 46 | B57: Платежи по кредиту (в валюте) | C57: Погашение + Проценты × (1 – Флаг капитализации) [стр.45 + стр.43 × (1 – стр.50)] | D57: =D56+D54*(1-D61) -> 0 | E57: =E56+E54*(1-E61) -> 33.3 | F57: =F56+F54*(1-F61) -> 33.3 | G57: =G56+G54*(1-G61) -> 33.3
A58: 47 | B58: Платежи по кредиту (в рублях) | C58: Платежи в валюте × курс [стр.46 × стр.39] | D58: =D57*D50 -> 0 | E58: =E57*E50 -> 99.9 | F58: =F57*F50 -> 99.9 | G58: =G57*G50 -> 99.9
A59: 48 | B59: Остаток кредита на конец периода | C59: Остаток на начало + выдачи – погашение + Проценты × Флаг капитализации [стр.38 + стр.41 – стр.45 + стр.43 × стр.48] | D59: =D49+D52-D56+D54*$D$61 -> 100 | E59: =E49+E52-E56+E54*$D$61 -> 72.9 | F59: =F49+F52-F56+F54*$D$61 -> 44.1198 | G59: =G49+G52-G56+G54*$D$61 -> 13.555228
A60: 49 | B60: Остаток кредита на конец (в рублях) | C60: Остаток в валюте × курс [стр.48 × стр.39] | D60: =D59*D50 -> 300 | E60: =E59*E50 -> 218.7 | F60: =F59*F50 -> 132.3594 | G60: =G59*G50 -> 40.665683
A61: 50 | B61: Флаг капитализации | C61: (0- без капитализации %. 1- с капитализацией %) | D61: 1 | E61: 1 | F61: 1 | G61: 1
B62: 3. Займы других организаций
A63: 51 | B63: Сумма займа на начало | C63: Равен остатку на конец предыдущего периода [стр.57 по графе t–1] | D63: 0 | E63: =D69 -> 200 | F63: =E69 -> 166 | G63: =F69 -> 116
A64: 52 | B64: Выдачи займа | C64: Вводимое значение | D64: 200 | E64: 0 | F64: 0 | G64: 0
A65: 53 | B65: Ставка займа (%) | C65: Вводимое значение | D65: 0.08 | E65: 0.08 | F65: 0.08 | G65: 0.08
A66: 54 | B66: Проценты по займу | C66: Ставка × Сумма займа на начало [стр.53 × стр.51] | D66: =D65*D63 -> 0 | E66: =E65*E63 -> 16 | F66: =F65*F63 -> 13.28 | G66: =G65*G63 -> 9.28
A67: 55 | B67: Погашение основного долга | C67: Вводимое значение | D67: 0 | E67: 50 | F67: 50 | G67: 100
A68: 56 | B68: Платежи по займу (денежные) | C68: Погашение + Проценты × (1 – Флаг капитализации) [стр.55 + стр.54 × (1 – стр.58)] | D68: =D67+D66*(1-D70) -> 0 | E68: =E67+E66*(1-E70) -> 50 | F68: =F67+F66*(1-F70) -> 63.28 | G68: =G67+G66*(1-G70) -> 109.28
A69: 57 | B69: Остаток займа на конец | C69: Сумма на начало + Выдачи – Погашение + Проценты × Флаг капитализации [стр.51 + стр.52 – стр.55 + стр.54 × стр.58] | D69: =D63+D64-D67+D66*D70 -> 200 | E69: =E63+E64-E67+E66*E70 -> 166 | F69: =F63+F64-F67+F66*F70 -> 116 | G69: =G63+G64-G67+G66*G70 -> 16
A70: 58 | B70: Флаг капитализации | C70: Вводимое значение по годам (0 или 1) | D70: 1 | E70: 1 | F70: 0 | G70: 0
A71: 59 | B71: Особые условия | C71: Текстовое поле: беспроцентный / отсрочка / конвертация в долю | D71: — | E71: — | F71: — | G71: —
B72: 4. Финансовая аренда (лизинг)
A73: 60 | B73: Остаток обязательств на начало | C73: Равен остатку на конец предыдущего периода [стр.68 по графе t–1] | D73: 0 | E73: =D81 -> 60 | F73: =E81 -> 40 | G73: =F81 -> 20
A74: 61 | B74: Новые договоры лизинга | C74: Вводимое значение | D74: 60 | E74: 0 | F74: 0 | G74: 0
A75: 62 | B75: Аванс (первоначальный платёж) | C75: Вводимое значение | D75: 0 | E75: 5 | F75: 0 | G75: 0
A76: 63 | B76: Ставка лизинга (%) | C76: Вводимое значение | D76: 0.1 | E76: 0.1 | F76: 0.1 | G76: 0.1
A77: 64 | B77: Проценты по лизингу | C77: Ставка × Остаток обязательств на начало [стр.63 × стр.60] | D77: =D76*D73 -> 0 | E77: =E76*E73 -> 6 | F77: =F76*F73 -> 4 | G77: =G76*G73 -> 2
A78: 65 | B78: Погашение основного долга | C78: Вводимое значение | D78: 0 | E78: 20 | F78: 20 | G78: 20
A79: 66 | B79: Выкупная стоимость | C79: Вводимое значение (платёж в конце срока) | D79: 0 | E79: 0 | F79: 0 | G79: 10
A80: 67 | B80: Платежи по лизингу (денежные) | C80: Аванс + Погашение + Выкупная стоимость + Проценты × (1 – Флаг капитализации) [стр.62 + стр.65 + стр.66 + стр.64 × (1 – стр.69)] | D80: =D75+D78+D79+D77*(1-D82) -> 0 | E80: =E75+E78+E79+E77*(1-E82) -> 31 | F80: =F75+F78+F79+F77*(1-F82) -> 24 | G80: =G75+G78+G79+G77*(1-G82) -> 32
A81: 68 | B81: Остаток обязательств на конец | C81: Остаток на начало + Новые договоры – Погашение + Проценты × Флаг капитализации [стр.60 + стр.61 – стр.65 + стр.64 × стр.69] | D81: =D73+D74-D78+D77*D82 -> 60 | E81: =E73+E74-E78+E77*E82 -> 40 | F81: =F73+F74-F78+F77*F82 -> 20 | G81: =G73+G74-G78+G77*G82 -> 0
A82: 69 | B82: Флаг капитализации | C82: Вводимое значение по годам (0 или 1) | D82: 0 | E82: 0 | F82: 0 | G82: 0
B83: 5. Ценные бумаги
A84: 70 | B84: Остаток обязательств на начало | C84: Равен остатку на конец предыдущего периода [стр.77 по графе t–1] | D84: 0 | E84: =D91 -> 250 | F84: =E91 -> 250 | G84: =F91 -> 200
A85: 71 | B85: Выпуск ценных бумаг | C85: Вводимое значение | D85: 250 | E85: 0 | F85: 0 | G85: 0
A86: 72 | B86: Номинал | C86: Вводимое значение | D86: 250 | E86: 250 | F86: 250 | G86: 250
A87: 73 | B87: Купонная ставка (%) | C87: Вводимое значение | D87: 0.12 | E87: 0.12 | F87: 0.12 | G87: 0.12
A88: 74 | B88: Купонные выплаты | C88: Купонная ставка × Номинал [стр.73 × стр.72 ] | D88: 0 | E88: =E87*E86 -> 30 | F88: =F87*F86 -> 30 | G88: =G87*G86 -> 30
A89: 75 | B89: Погашение номинала | C89: Вводимое значение | D89: 0 | E89: 0 | F89: 50 | G89: 200
A90: 76 | B90: Платежи по ценным бумагам | C90: Купонные выплаты + Погашение × (1 – Флаг капитализации) [стр.74 + стр.75 × (1 – стр.78)] | D90: 0 | E90: =E88+E89*(1-E92) -> 30 | F90: =F88+F89*(1-F92) -> 80 | G90: =G88+G89*(1-G92) -> 230
A91: 77 | B91: Остаток обязательств на конец | C91: Остаток на начало + Выпуск – Погашение + Купонные выплаты × Флаг капитализации [стр.70 + стр.71 – стр.75 + стр.74 × стр.78] | D91: =D84+D85-D89+D88*D92 -> 250 | E91: =E84+E85-E89+E88*E92 -> 250 | F91: =F84+F85-F89+F88*F92 -> 200 | G91: =G84+G85-G89+G88*G92 -> 0
A92: 78 | B92: Флаг капитализации | C92: Вводимое значение по годам (0 или 1) | D92: 0 | E92: 0 | F92: 0 | G92: 0
B93: 6. Государственное участие
A94: 79 | B94: Компенсация процентов | C94: Вводимое значение (уменьшает расходы по кредитам) | D94: 0 | E94: 20 | F94: 0 | G94: 0
A95: 80 | B95: Субсидии/гранты | C95: Вводимое значение (положительный поток) | D95: 0 | E95: 0 | F95: 30 | G95: 0
A96: 81 | B96: Гарантии | C96: Текстовое поле (неденежный поток, отражается в разделе «Риски») | D96: — | E96: — | F96: — | G96: —
A97: 82 | B97: Итоговый эффект на расходы | C97: Компенсация процентов – (не влияет на остаток долга) [стр.79 ] | D97: =-D94 -> 0 | E97: =-E94 -> -20 | F97: =-F94 -> 0 | G97: =-G94 -> 0
A98: 83 | B98: Итоговый эффект на притоки | C98: Субсидии/гранты – положительный поток [стр.80 ] | D98: =D95 -> 0 | E98: =E95 -> 0 | F98: =F95 -> 30 | G98: =G95 -> 0
A99: 84 | B99: Сводный результат | C99: Сумма эффектов на расходы[-(стр.79 + стр.80) ] | D99: =-D94-D95 -> 0 | E99: =-E94-E95 -> -20 | F99: =-F94-F95 -> -30 | G99: =-G94-G95 -> 0
B100: 7. Существующие долгосрочные кредиты, займы организации
...

Sheet 4.Оценка проекта 
B2: Выпадающий список
A3: Отрасль (ОКЭД) | B3: 011 Выращивание одно- или двухлетних культур
A4: ="Итоговая оценка проекта" -> Итоговая оценка проекта
B5: Базовый вариант оценки | C5: Оценка при стрессе | E5: Общая оценка проекта
A6: Оценка финансовой устойчивости | B6: =IF(COUNTIF(G11:G15,"Да*")=ROW(G11:G15),"Финансовая устойчивость: соответствует", IF(COUNTIF(G11:G15,"Да*")>=3,"Финансовая устойчивость: частично соответствует", "Финансовая устойчивость: не соответствует")) -> Финансовая устойчивость: частично соответствует | C6: =IF(COUNTIF(I11:I15,"Да*")=5,"Финансовая устойчивость (стресс): соответствует", IF(COUNTIF(I11:I15,"Да*")>=3,"Финансовая устойчивость (стресс): частично соответствует", "Финансовая устойчивость (стресс): не соответствует")) -> Финансовая устойчивость (стресс): частично соответствует
A7: Оценка эффективности проекта | B7: =IF(COUNTIF(G17:G21,"Да*")=5,"Эффективность проекта: соответствует", IF(COUNTIF(G17:G21,"Да*")>=3,"Эффективность проекта: частично соответствует", "Эффективность проекта: не соответствует")) -> Эффективность проекта: не соответствует | C7: =IF(COUNTIF(I17:I22,"Да*")=6,"Эффективность проекта (стресс): соответствует", IF(COUNTIF(I17:I22,"Да*")>=3,"Эффективность проекта (стресс): частично соответствует", "Эффективность проекта (стресс): не соответствует")) -> Эффективность проекта (стресс): не соответствует
A8: Общий вывод | B8: =IF( AND(B6="соответствует",B7="соответствует"), "Базовый вариант: соответствует", IF( OR(B6="не соответствует",B7="не соответствует"), "Базовый вариант: не соответствует", "Базовый вариант: частично соответствует" ) ) -> Базовый вариант: частично соответствует | C8: =IF( OR(ISNUMBER(SEARCH("не соответствует",C6)),ISNUMBER(SEARCH("не соответствует",C7))), "Стресс-сценарий: не соответствует", IF( AND(ISNUMBER(SEARCH("соответствует",C6)),ISNUMBER(SEARCH("соответствует",C7))), "Стресс-сценарий: соответствует", "Стресс-сценарий: частично соответствует" ) ) -> Стресс-сценарий: не соответствует | E8: =IF( C8="Стресс-сценарий: не соответствует", "❌ Проект не соответствует ряду нормативов и требует доработки", IF( AND(B8="Базовый вариант: соответствует",C8="Стресс-сценарий: соответствует"), "✅ Проект соответствует нормативам в базовом и стресс‑сценарии", "⚠️ Проект частично соответствует (требует доработки)" ) ) -> ❌ Проект не соответствует ряду нормативов и требует доработки
A9: Оценка основных показателей проекта.
A10: Показатель | B10: Формула | C10: Среднее значение по проекту | D10: Среднее значение по стресс сценарию | E10: Норматив (≥) | F10: Источник норматива | G10: Оценка базового проекта (соответствие) | H10: Знак светофора для базового проекта | I10: Оценка проекта при стрессах (соответствие) | J10: Знак светофора для стрессового сценария | K10: Комментарий для базового варианта (автоматическое заполнение) | L10: Комментарий для стрессового варианта (автоматичнское заполение
A11: Коэффициент покрытия задолженности (Кпз) | B11: Денежный поток / (погашение основного долга + погашение процентов) | C11: =AVERAGE('3.Исх проект данные и риски '!E108:G108) -> 1.0406888 | D11: =AVERAGE('3.Исх проект данные и риски '!E141:G141) -> 0.123327 | E11: 1.3 | F11: Постановление Министерства экономики Республики Беларусь от 31 августа 2005 г. № 158 | G11: =IF(C11="","",IF(C11>=E11,"Да",IF(C11>=E11*0.9,"Пограничное","Нет"))) -> Нет | H11: =IF(G11="Да",1,IF(G11="Пограничное",0.5,IF(G11="Нет",0,""))) -> 0 | I11: =IF(D11="","",IF(D11>=E11,"Да",IF(D11>=E11*0.9,"Пограничное","Нет"))) -> Нет | J11: =IF(I11="Да",1,IF(I11="Пограничное",0.5,IF(I11="Нет",0,""))) -> 0 | K11: =IF(G11="Да","Показатель соответствует нормативу", IF(G11="Пограничное","Показатель близок к нормативу", IF(G11="Нет","Показатель ниже нормативного уровня",""))) -> Показатель ниже нормативного уровня | L11: =IF(I11="Да","Устойчивость сохранена", IF(I11="Пограничное","Показатель на грани устойчивости", IF(I11="Нет","Показатель просел ниже нормы",""))) -> Показатель просел ниже нормы
A12: Коэффициент покрытия процентов | B12: (Прибыль до налогообложения +процентные платежи)/процентные платежи | C12: =AVERAGE('3.Исх проект данные и риски '!E109:G109) -> 7.7173643 | D12: =AVERAGE('3.Исх проект данные и риски '!E142:G142) -> 2.2176106 | E12: 2 | G12: =IF(C12="","",IF(C12>=E12,"Да",IF(C12>=E12*0.9,"Пограничное","Нет"))) -> Да | H12: =IF(G12="Да",1,IF(G12="Пограничное",0.5,IF(G12="Нет",0,""))) -> 1 | I12: =IF(D12="","",IF(D12>=E12,"Да",IF(D12>=E12*0.9,"Пограничное","Нет"))) -> Да | J12: =IF(I12="Да",1,IF(I12="Пограничное",0.5,IF(I12="Нет",0,""))) -> 1 | K12: =IF(G12="Да","Показатель соответствует нормативу", IF(G12="Пограничное","Показатель близок к нормативу", IF(G12="Нет","Показатель ниже нормативного уровня",""))) -> Показатель соответствует нормативу | L12: =IF(I12="Да","Устойчивость сохранена", IF(I12="Пограничное","Показатель на грани устойчивости", IF(I12="Нет","Показатель просел ниже нормы",""))) -> Устойчивость сохранена
A13: Коэффициент текущей ликвидности | B13: Краткосрочные активы / Краткосрочные обязательства | C13: =AVERAGE('3.Исх проект данные и риски '!E31:G31) -> 1.4065147 | D13: =AVERAGE('3.Исх проект данные и риски '!E143:G143) -> 1.4173361 | E13: =VLOOKUP($B$3,'5.Отрасл нормативы и WACC '!$C$2:$I$175,2,FALSE) -> 1.5 | F13: Данные Лист 5, на основе Постановления Совмина №167 | G13: =IF(C13="","",IF(C13>=E13,"Да",IF(C13>=E13*0.9,"Пограничное","Нет"))) -> Пограничное | H13: =IF(G13="Да",1,IF(G13="Пограничное",0.5,IF(G13="Нет",0,""))) -> 0.5 | I13: =IF(D13="","",IF(D13>=E13,"Да",IF(D13>=E13*0.9,"Пограничное","Нет"))) -> Пограничное | J13: =IF(I13="Да",1,IF(I13="Пограничное",0.5,IF(I13="Нет",0,""))) -> 0.5 | K13: =IF(G13="Да","Ликвидность соответствует нормативу", IF(G13="Пограничное","Ликвидность близка к нормативу", IF(G13="Нет","Ликвидность ниже нормативного уровня",""))) -> Ликвидность близка к нормативу | L13: =IF(I13="Да","Устойчивость сохранена", IF(I13="Пограничное","Ликвидность на грани устойчивости", IF(I13="Нет","Ликвидность просела ниже нормы",""))) -> Ликвидность на грани устойчивости
A14: Коэффициент обеспеченности собственными оборотными средствами | B14: (собственный капитал + долгосрочные обязательства - долгосрочные активы) / краткосрочные активы | C14: =AVERAGE('3.Исх проект данные и риски '!E33:G33) -> 1.9276307 | D14: =AVERAGE('3.Исх проект данные и риски '!E144:G144) -> 1.8311786 | E14: =VLOOKUP($B$3,'5.Отрасл нормативы и WACC '!$C$2:$I$175,3,FALSE) -> 0.2 | F14: Данные Лист 5, на основе Постановления Совмина №167 | G14: =IF(C14="","",IF(C14>=E14,"Да",IF(C14>=E14*0.9,"Пограничное","Нет"))) -> Да | H14: =IF(G14="Да",1,IF(G14="Пограничное",0.5,IF(G14="Нет",0,""))) -> 1 | I14: =IF(D14="","",IF(D14>=E14,"Да",IF(D14>=E14*0.9,"Пограничное","Нет"))) -> Да | J14: =IF(I14="Да",1,IF(I14="Пограничное",0.5,IF(I14="Нет",0,""))) -> 1 | K14: =IF(G14="Да","Обеспеченность собственными оборотными средствами соответствует нормативу", IF(G14="Пограничное","Обеспеченность собственными оборотными средствами близка к нормативу", IF(G14="Нет","Обеспеченность собственными оборотными средствами ниже нормативного уровня",""))) -> Обеспеченность собственными оборотными средствами соответствует нормативу | L14: =IF(I14="Да","Обеспеченность собственными оборотными средствами сохраняется в стрессовом сценарии", IF(I14="Пограничное","Обеспеченность собственными оборотными средствами на грани устойчивости в стрессовом сценарии", IF(I14="Нет","Обеспеченность собственными оборотными средствами просела ниже нормы в стрессовом сценарии",""))) -> Обеспеченность собственными оборотными средствами сохраняется в стрессовом сценарии
A15: Коэффициент обеспеченности обязательств активами (Ка) | B15: Обязательства/Активы | C15: =AVERAGE('3.Исх проект данные и риски '!E34:G34) -> 0.61832981 | D15: =AVERAGE('3.Исх проект данные и риски '!E145:G145) -> 0.60760742 | E15: =VLOOKUP($B$3,'5.Отрасл нормативы и WACC '!$C$2:$I$175,4,FALSE) -> 0.85 | F15: Лист 5, согласно Норамативно- правовым актам | G15: =IF(C15="","",IF(C15<=E15,"Да",IF(C15<=E15*1.1,"Пограничное","Нет"))) -> Да | H15: =IF(G15="Да",1,IF(G15="Пограничное",0.5,IF(G15="Нет",0,""))) -> 1 | I15: =IF(D15="","",IF(D15<=E15,"Да",IF(D15<=E15*1.1,"Пограничное","Нет"))) -> Да | J15: =IF(I15="Да",1,IF(I15="Пограничное",0.5,IF(I15="Нет",0,""))) -> 1 | K15: =IF(G15="Да","Коэффициент обеспеченности обязательств активами соответствует нормативу, долговая нагрузка находится в допустимых пределах", IF(G15="Пограничное","Коэффициент обеспеченности обязательств активами близок к нормативу, долговая нагрузка повышена", IF(G15="Нет","Коэффициент обеспеченности обязательств активами превышает норматив, долговая нагрузка чрезмерна",""))) -> Коэффициент обеспеченности обязательств активами соответствует нормативу, долговая нагрузка находится в допустимых пределах | L15: =IF(I15="Да","Коэффициент обеспеченности обязательств активами сохраняется в пределах нормы даже при стрессовом сценарии", IF(I15="Пограничное","Коэффициент обеспеченности обязательств активами на грани устойчивости в стрессовом сценарии", IF(I15="Нет","Коэффициент обеспеченности обязательств активами выходит за пределы нормы в стрессовом сценарии",""))) -> Коэффициент обеспеченности обязательств активами сохраняется в пределах нормы даже при стрессовом сценарии
A16: Коэффициент автономии | B16: Собственный капитал / Активы | C16: =AVERAGE('3.Исх проект данные и риски '!E32:G32) -> 0.76553258 | D16: =AVERAGE('3.Исх проект данные и риски '!E148:G148) -> 0.74610125 | E16: =VLOOKUP($B$3,'5.Отрасл нормативы и WACC '!$C$2:$I$175,6,FALSE) -> 0.5 | F16: Данные Лист 5, на основе Постановления Совмина №167 | G16: =IF(C16="","",IF(C16>=E16,"Да",IF(C16>=E16*0.9,"Пограничное","Нет"))) -> Да | H16: =IF(G16="Да",1,IF(G16="Пограничное",0.5,IF(G16="Нет",0,""))) -> 1 | I16: =IF(D16="","",IF(D16>=E16,"Да",IF(D16>=E16*0.9,"Пограничное","Нет"))) -> Да | J16: =IF(I16="Да",1,IF(I16="Пограничное",0.5,IF(I16="Нет",0,""))) -> 1 | K16: =IF(G16="Да","Коэффициент автономии соответствует нормативу, доля собственного капитала в активах достаточна", IF(G16="Пограничное","Коэффициент автономии близок к нормативу, устойчивость компании ограничена", IF(G16="Нет","Коэффициент автономии ниже нормативного уровня, зависимость от заемных средств высока",""))) -> Коэффициент автономии соответствует нормативу, доля собственного капитала в активах достаточна | L16: =IF(I16="Да","Коэффициент автономии сохраняется в пределах нормы даже при стрессовом сценарии", IF(I16="Пограничное","Коэффициент автономии на грани устойчивости в стрессовом сценарии", IF(I16="Нет","Коэффициент автономии выходит за пределы нормы в стрессовом сценарии, зависимость от заемных средств усиливается",""))) -> Коэффициент автономии сохраняется в пределах нормы даже при стрессовом сценарии
A17: Рентабельность активов (ROA) | B17: Чистая прибыль / Активы(среднегодовые) | C17: =AVERAGE('3.Исх проект данные и риски '!E35:G35) -> 0.16005189 | D17: =AVERAGE('3.Исх проект данные и риски '!E146:G146) -> 0.076230981 | E17: =VLOOKUP($B$3,'5.Отрасл нормативы и WACC '!$C$2:$I$175,5,FALSE) -> 0.03 | F17: Рассчитывается среднеотраслевое значение на основе данные Белстата. | G17: =IF(C17="","",IF(C17>=E17,"Да",IF(C17>=E17*0.9,"Пограничное","Нет"))) -> Да | H17: =IF(G17="Да",1,IF(G17="Пограничное",0.5,IF(G17="Нет",0,""))) -> 1 | I17: =IF(D17="","",IF(D17>=E17,"Да",IF(D17>=E17*0.9,"Пограничное","Нет"))) -> Да | J17: =IF(I17="Да",1,IF(I17="Пограничное",0.5,IF(I17="Нет",0,""))) -> 1 | K17: =IF(G17="Да","Рентабельность активов соответствует нормативу, эффективность использования активов достаточна", IF(G17="Пограничное","Рентабельность активов близка к нормативу, эффективность использования активов ограничена", IF(G17="Нет","Рентабельность активов ниже нормативного уровня, активы используются недостаточно эффективно",""))) -> Рентабельность активов соответствует нормативу, эффективность использования активов достаточна | L17: =IF(I17="Да","Рентабельность активов сохраняется в пределах нормы даже при стрессовом сценарии", IF(I17="Пограничное","Рентабельность активов на грани устойчивости в стрессовом сценарии", IF(I17="Нет","Рентабельность активов выходит за пределы нормы в стрессовом сценарии, эффективность использования активов снижается",""))) -> Рентабельность активов сохраняется в пределах нормы даже при стрессовом сценарии
A18: Рентабельность капитала (ROE) | B18: Чистая прибыль / Собственный капитал(среднегодовой) | C18: =AVERAGE('3.Исх проект данные и риски '!E36:G36) -> 0.20941052 | D18: =AVERAGE('3.Исх проект данные и риски '!E147:G147) -> 0.10211575 | E18: =VLOOKUP($B$3,'5.Отрасл нормативы и WACC '!$C$2:$M$175,11,FALSE) -> 0.0057186065 | F18: Рассчитывается среднеотраслевое значение на основе данные Белстата. | G18: =IF(C18="","",IF(C18>=E18,"Да",IF(C18>=E18*0.9,"Пограничное","Нет"))) -> Да | H18: =IF(G18="Да",1,IF(G18="Пограничное",0.5,IF(G18="Нет",0,""))) -> 1 | I18: =IF(D18="","",IF(D18>=E18,"Да",IF(D18>=E18*0.9,"Пограничное","Нет"))) -> Да | J18: =IF(I18="Да",1,IF(I18="Пограничное",0.5,IF(I18="Нет",0,""))) -> 1 | K18: =IF(G18="Да","Рентабельность капитала (ROE) превышает среднеотраслевую, проект обеспечивает доходность выше средней", IF(G18="Пограничное","Рентабельность капитала (ROE) близка к средней, доходность на грани достаточности", IF(G18="Нет","Рентабельность капитала (ROE) ниже средней",""))) -> Рентабельность капитала (ROE) превышает среднеотраслевую, проект обеспечивает доходность выше средней | L18: =IF(I18="Да","Рентабельность капитала (ROE) остаётся выше WACC даже в стрессовом сценарии", IF(I18="Пограничное","Рентабельность капитала (ROE) близка к WACC в стрессовом сценарии, устойчивость ограничена", IF(I18="Нет","Рентабельность капитала (ROE) падает ниже WACC в стрессовом сценарии, проект теряет инвестиционную привлекательность",""))) -> Рентабельность капитала (ROE) остаётся выше WACC даже в стрессовом сценарии
A19: Ставка по заемным средствам | B19: Средневзвешенная ставка по всем заемным средствам | C19: =AVERAGE('3.Исх проект данные и риски '!E118:G118) -> 0.094337163 | D19: =AVERAGE('3.Исх проект данные и риски '!E129:G129) -> 0.1004795 | E19: =VLOOKUP(B3,'5.Отрасл нормативы и WACC '!$C$2:$N$175,12,FALSE) -> 0.090460215 | F19: Рассчеты на основе данных НБРБ | G19: =IF(E19="","н/д",IF(C19 > E19, "Нет", "Да")) -> Нет | H19: =IF(G19="Да",1,IF(G19="Пограничное",0.5,IF(G19="Нет",0,""))) -> 0 | I19: =IF(D19="","",IF(D19 > E19, "Нет", "Да")) -> Нет | J19: =IF(I19="Да",1,IF(I19="Пограничное",0.5,IF(I19="Нет",0,""))) -> 0 | K19: =IF(G19="Да","Средневзвешенная ставка по заемным средствам соответствует нормативу, стоимость привлечения капитала допустима", IF(G19="Пограничное","Средневзвешенная ставка по заемным средствам близка к нормативу, стоимость капитала повышена", IF(G19="Нет","Средневзвешенная ставка по заемным средствам превышает норматив, стоимость привлечения капитала чрезмерна",""))) -> Средневзвешенная ставка по заемным средствам превышает норматив, стоимость привлечения капитала чрезмерна | L19: =IF(I19="Да","Средневзвешенная ставка по заемным средствам сохраняется в пределах нормы даже при стрессовом сценарии", IF(I19="Пограничное","Средневзвешенная ставка по заемным средствам на грани устойчивости в стрессовом сценарии", IF(I19="Нет","Средневзвешенная ставка по заемным средствам выходит за пределы нормы в стрессовом сценарии, стоимость капитала становится чрезмерной",""))) -> Средневзвешенная ставка по заемным средствам выходит за пределы нормы в стрессовом сценарии, стоимость капитала становится чрезмерной
A20: Предел ставки кредита | B20: Макс. ставка кредита при DSCR ≥ 1,5 | C20: ='6.Расчет предельной ставки'!B4 -> 8 | D20: ='6.Расчет предельной ставки'!G4 -> -0.47834245 | F20: На Листе 6 определяется максимальная ставка, которую проект может выдержать, сохраняя при этом безопасный уровень DSCR 1,5. | G20: =IF(D20>0,"Да","Нет") -> Нет | H20: =IF(G20="Да",1,IF(G20="Пограничное",0.5,IF(G20="Нет",0,""))) -> 0 | I20: =IF(D20>0,"Да","Нет") -> Нет | J20: =IF(I20="Да",1,IF(I20="Пограничное",0.5,IF(I20="Нет",0,""))) -> 0 | K20: =IF(G20="Да","Норматив DSCR ≥ 1,2 выполняется при положительной ставке", "Норматив DSCR ≥ 1,2 недостижим при положительной ставке, возвратность под риском") -> Норматив DSCR ≥ 1,2 недостижим при положительной ставке, возвратность под риском
A21: Внутренняя норма доходности (ВНД) | B21: ВНД (денежные потоки) | C21: ='3.Исх проект данные и риски '!D19 -> 0.2702066 | D21: ='3.Исх проект данные и риски '!D153 -> -0.22376689 | E21: =VLOOKUP(B3,'5.Отрасл нормативы и WACC '!$C$35:$M$175,8,FALSE) -> #N/A | F21: Показатель ВНД сравнивается с барьерной ставкой WACC отрасли. Проект эффективен, если ВНД > WACC. | G21: =IF(C21="","",IF(C21>=E21,"Да",IF(C21>=E21*0.9,"Пограничное","Нет"))) -> #N/A | H21: =IF(G21="Да",1,IF(G21="Пограничное",0.5,IF(G21="Нет",0,""))) -> #N/A | I21: =IF(D21="","",IF(D21<E21,"Нет",IF(D21<=E21*1.1,"Да","Пограничное"))) -> #N/A | J21: =IF(I21="Да",1,IF(I21="Пограничное",0.5,IF(I21="Нет",0,""))) -> #N/A | K21: =IF(G21="Да","ВНД превышает норматив, проект обеспечивает доходность выше стоимости капитала", "ВНД ниже нормативного уровня, проект требует пересмотра доходности") -> #N/A | L21: =IF(I21="Да","ВНД в стресс-сценарии сохраняется выше нуля", "ВНД в стресс-сценарии отрицательная, проект теряет инвестиционную привлекательность") -> #N/A
A22: Чувствительность NPV | B22: (NPV_стресс – NPV_база) / NPV_база | D22: ='3.Исх проект данные и риски '!D152 -> -2.6700657 | I22: =IF(D22>=-0.1,"Да","Нет") -> Нет | J22: =IF(I22="Да",1,IF(I22="Пограничное",0.5,IF(I22="Нет",0,""))) -> 0 | L22: =IF(I22="Да","Чувствительность NPV в пределах нормы, устойчивость доходности сохраняется", "Чувствительность NPV критическая, доходность проекта уязвима") -> Чувствительность NPV критическая, доходность проекта уязвима

Sheet 5.Отрасл нормативы и WACC 
A1: Вид деятельности | B1: oked3 | C1: Вид деят - окед | D1: Коэффициент текущей ликвидности | E1: Коэффициент обеспеченности собственными оборотными средствами | F1: Коэффициент обеспеченности обязательств активами | G1: Рентабельность активов (≥ ) | H1: Коэффициент автономии (буфер собственного капитала): диапазон 0,4-0,6) | I1: Финансовый леверидж (отношение долга к собственному капиталу ) (<1, 05-07) | J1: WACC (проекты) | K1: WACC (текущая) | L1: Рентабельность активов (среднеотраслева за последние 12 кварталов-2022-2024 г.г.) | M1: Рентабельность собственного капитала (среднеотраслева за последние 12 кварталов-2022-2024 г.г.) | N1: Средневзвешенные ставки по вновь выданным кредитам (2024год)
A2: Выращивание одно- или двухлетних культур | B2: 011 | C2: 011 Выращивание одно- или двухлетних культур | D2: 1.5 | E2: 0.2 | F2: 0.85 | G2: 0.03 | H2: 0.5 | I2: 0.7 | J2: 0.10042709 | K2: 0.09654768 | L2: 0.01186405 | M2: 0.0057186065 | N2: 0.090460215
A3: Выращивание многолетних культур | B3: 012 | C3: 012 Выращивание многолетних культур | D3: 1.5 | E3: 0.2 | F3: 0.85 | G3: 0.03 | H3: 0.5 | I3: 0.7 | J3: 0.11956232 | K3: 0.1186175 | L3: 0.014733034 | M3: 0.0094596175 | N3: 0.091881304
A4: Производство продукции питомников | B4: 013 | C4: 013 Производство продукции питомников | D4: 1.5 | E4: 0.2 | F4: 0.85 | G4: 0.03 | H4: 0.5 | I4: 0.7 | J4: 0.12457705 | K4: 0.12458438 | L4: 0.044309363 | M4: 0.033882249 | N4: 0.10201286
A5: Животноводство | B5: 014 | C5: 014 Животноводство | D5: 1.5 | E5: 0.2 | F5: 0.85 | G5: 0.03 | H5: 0.5 | I5: 0.7 | J5: 0.1024425 | K5: 0.097782984 | L5: 0.018049803 | M5: 0.0095879994 | N5: 0.084222918
A6: Смешанное сельское хозяйство | B6: 015 | C6: 015 Смешанное сельское хозяйство | D6: 1.5 | E6: 0.2 | F6: 0.85 | G6: 0.03 | H6: 0.5 | I6: 0.7 | J6: 0.084019432 | K6: 0.077156634 | L6: 0.15349498 | M6: 0.039379407 | N6: 0.066950626
A7: Деятельность, способствующая выращиванию сельскохозяйственных культур и разведению животных | B7: 016 | C7: 016 Деятельность, способствующая выращиванию сельскохозяйственных культур и разведению животных | D7: 1.5 | E7: 0.2 | F7: 0.85 | G7: 0.03 | H7: 0.5 | I7: 0.7 | J7: 0.11951458 | K7: 0.11589512 | L7: 0.0016406995 | M7: 0.0012673988 | N7: 0.10189034
A8: Охота и отлов, включая предоставление услуг в этих областях | B8: 017 | C8: 017 Охота и отлов, включая предоставление услуг в этих областях | D8: 1.5 | E8: 0.2 | F8: 0.85 | G8: 0.03 | H8: 0.5 | I8: 0.7 | J8: 0.10213825 | K8: 0.10328501 | N8: 0
A9: Лесоводство и прочая лесохозяйственная деятельность | B9: 021 | C9: 021 Лесоводство и прочая лесохозяйственная деятельность | D9: 1.5 | E9: 0.2 | F9: 0.85 | G9: 0.03 | H9: 0.5 | I9: 0.7 | J9: 0.10213825 | K9: 0.10328501 | L9: 0.05285202 | M9: 0.021018021 | N9: 0.082766666
A10: Лесозаготовки | B10: 022 | C10: 022 Лесозаготовки | D10: 1.5 | E10: 0.2 | F10: 0.85 | G10: 0.03 | H10: 0.5 | I10: 0.7 | J10: 0.083629818 | K10: 0.091427164 | L10: 0.16327187 | M10: -0.012033631 | N10: 0.10594734
A11: Услуги, связанные с лесоводством и лесозаготовками | B11: 024 | C11: 024 Услуги, связанные с лесоводством и лесозаготовками | D11: 1.5 | E11: 0.2 | F11: 0.85 | G11: 0.03 | H11: 0.5 | I11: 0.7 | J11: 0.0965975 | K11: 0.10356629 | L11: 0.032991659 | M11: 0.0097384527 | N11: 0.11006666
A12: Рыбоводство | B12: 032 | C12: 032 Рыбоводство | D12: 1.5 | E12: 0.2 | F12: 0.85 | G12: 0.03 | H12: 0.5 | I12: 0.7 | J12: 0.1123635 | K12: 0.11580487 | L12: 0.015245588 | M12: 0.0090984581 | N12: 0.089400005
A13: Добыча нефти | B13: 061 | C13: 061 Добыча нефти | D13: 1.7 | E13: 0.3 | F13: 0.85 | G13: 0.03 | H13: 0.5 | I13: 0.7 | J13: 0.14784943 | K13: 0.12395281 | L13: 0.021829169 | M13: 0.018622294 | N13: 0.11303868
A14: Добыча камня, песка и глины | B14: 081 | C14: 081 Добыча камня, песка и глины | D14: 1.7 | E14: 0.3 | F14: 0.85 | G14: 0.03 | H14: 0.5 | I14: 0.7 | J14: 0.11365321 | K14: 0.11285055 | L14: 0.013917343 | M14: 0.0091120778 | N14: 0.11303868
A15: Переработка и консервирование мяса и производство мясной и мясосодержащей продукции | B15: 101 | C15: 101 Переработка и консервирование мяса и производство мясной и мясосодержащей продукции | D15: 1.3 | E15: 0.2 | F15: 0.85 | G15: 0.03 | H15: 0.5 | I15: 0.7 | J15: 0.094533281 | K15: 0.09269412 | L15: 0.033241015 | M15: 0.011948114 | N15: 0.094843493
A16: Переработка и консервирование рыбы, ракообразных и моллюсков | B16: 102 | C16: 102 Переработка и консервирование рыбы, ракообразных и моллюсков | D16: 1.7 | E16: 0.3 | F16: 0.85 | G16: 0.03 | H16: 0.5 | I16: 0.7 | J16: 0.1194552 | K16: 0.11838358 | L16: 0.052929852 | M16: 0.041161794 | N16: 0.10588926
A17: Переработка и консервирование фруктов и овощей | B17: 103 | C17: 103 Переработка и консервирование фруктов и овощей | D17: 1.7 | E17: 0.3 | F17: 0.85 | G17: 0.03 | H17: 0.5 | I17: 0.7 | J17: 0.099715652 | K17: 0.107901 | L17: 0.047894839 | M17: 0.01560412 | N17: 0.12018336
A18: Производство растительных и животных масел и жиров | B18: 104 | C18: 104 Производство растительных и животных масел и жиров | D18: 1.3 | E18: 0.2 | F18: 0.85 | G18: 0.03 | H18: 0.5 | I18: 0.7 | J18: 0.098310299 | K18: 0.10594019 | L18: 0.17675635 | M18: 0.073079214 | N18: 0.078403292
A19: Производство молочных продуктов | B19: 105 | C19: 105 Производство молочных продуктов | D19: 1.3 | E19: 0.2 | F19: 0.85 | G19: 0.03 | H19: 0.5 | I19: 0.7 | J19: 0.10282457 | K19: 0.099174156 | L19: 0.035623249 | M19: 0.017273467 | N19: 0.10005049
A20: Производство мукомольно-крупяных продуктов, крахмалов и крахмальных продуктов | B20: 106 | C20: 106 Производство мукомольно-крупяных продуктов, крахмалов и крахмальных продуктов | D20: 1.3 | E20: 0.2 | F20: 0.85 | G20: 0.03 | H20: 0.5 | I20: 0.7 | J20: 0.093821507 | K20: 0.099320498 | L20: -0.0017676569 | M20: -8.1688144e-05 | N20: 0.086833334
... A175: Научные исследования и разработки в области общественных и гуманитарных наук | B175: 722 | C175: 722 Научные исследования и разработки в области общественных и гуманитарных наук | D175: 1.15 | E175: 0.2 | F175: 0.85 | G175: 0.1 | H175: 0.5 | I175: 0.7 | J175: 0.093107834 | K175: 0.10950155 | L175: 0.042603161 | M175: 0.018142244 | N175: 0.10070168

Sheet 6.Расчет предельной ставки
A1: Значение ставки рассчитывается через функцию поиск параметров поиск параметров в ячейке "Мин. Коэффициент покрытия задолженности (красный шрифт)
A2: Для базового сценария | F2: Для стресс сценария
A3: Параметр | B3: Значение | C3: Формула / Результат | F3: Параметр | G3: Значение | H3: Формула / Результат
A4: Ставка кредита | B4: 8 | C4: =PMT(B4,B5,-B6) -> 4806.5934 | F4: Ставка кредита | G4: -0.47834245 | H4: =PMT(G4,G5,-G6) -> 47.482936
A5: Срок кредита | B5: 3 | F5: Срок кредита | G5: 3
A6: Сумма кредита | B6: 600 | F6: Сумма кредита | G6: 600
A7: Ежегодные выплаты (при параметрах ставках срока и суммы)
A8: Денежный поток год 1 | B8: 222 | C8: =B8/$C$4 -> 0.046186557 | D8: Коэффициент покрытия задолженности | F8: Денежный поток год 1 | G8: 176.046 | H8: =G8/$H$4 -> 3.7075635 | I8: Коэффициент покрытия задолженности
A9: Денежный поток год 2 | B9: 294 | C9: =B9/$C$4 -> 0.061165981 | D9: Коэффициент покрытия задолженности | F9: Денежный поток год 2 | G9: 164.09402 | H9: =G9/$H$4 -> 3.4558525 | I9: Коэффициент покрытия задолженности
A10: Денежный поток год 3 | B10: 327 | C10: =B10/$C$4 -> 0.06803155 | D10: Коэффициент покрытия задолженности | F10: Денежный поток год 3 | G10: 71.221225 | H10: =G10/$H$4 -> 1.4999331 | I10: Коэффициент покрытия задолженности
A11: Мин. Коэффициент покрытия задолженности (DSCR) | C11: =MIN(C8:C10) -> 0.046186557 | F11: Мин. Коэффициент покрытия задолженности (DSCR) | H11: =MIN(H8:H10) -> 1.4999331
A12: Норматив DSCR | B12: 1.5 | F12: Норматив DSCR | G12: 1.5
